Workbook

Sheet Assumptions
B2: Ørsted A/S — DCF Valuation Model
B3: Assumptions and key drivers (DKK billions, except per-share and ratios)
B4: Author: Md Nazmul Islam Ishan · Illustrative model
B6: 1. Revenue and operating drivers
C7: 2024A | D7: 2025E | E7: 2026E | F7: 2027E | G7: 2028E | H7: 2029E
B8: Revenue (DKK bn) | C8: 71.4 | D8: =C8*(1+C9) | E8: =D8*(1+D9) | F8: =E8*(1+E9) | G8: =F8*(1+F9) | H8: =G8*(1+G9)
B9: Revenue growth % | C9: 0 | D9: 0.06 | E9: 0.07 | F9: 0.07 | G9: 0.05 | H9: 0.04
B10: EBITDA margin % | C10: 0.245 | D10: 0.255 | E10: 0.26 | F10: 0.265 | G10: 0.265 | H10: 0.26
B11: D&A as % revenue | C11: 0.11 | D11: 0.11 | E11: 0.108 | F11: 0.105 | G11: 0.102 | H11: 0.1
B12: Effective tax rate % | C12: 0.22 | D12: 0.22 | E12: 0.22 | F12: 0.22 | G12: 0.22 | H12: 0.22
B14: 2. Capex and working capital
C15: 2024A | D15: 2025E | E15: 2026E | F15: 2027E | G15: 2028E | H15: 2029E
B16: Capex as % revenue | C16: 0.32 | D16: 0.3 | E16: 0.26 | F16: 0.22 | G16: 0.18 | H16: 0.14
B17: Working capital change (% rev) | C17: 0.02 | D17: 0.02 | E17: 0.015 | F17: 0.012 | G17: 0.01 | H17: 0.01
B19: 3. Terminal value and discounting
B20: Terminal growth rate (g) | C20: 0.02
B21: Discount rate (WACC) — see WACC sheet | C21: =WACC!C15
B23: 4. Capital structure and shares
B24: Net debt (DKK bn) — most recent reporting | C24: 53
B25: Diluted shares outstanding (millions) | C25: 420.1
B27: Note: All figures are illustrative for modelling demonstration. Re-validate against latest Ørsted Annual Report before use.

Sheet Income Statement
B2: Income Statement Forecast (DKK bn)
C4: 2024A | D4: 2025E | E4: 2026E | F4: 2027E | G4: 2028E | H4: 2029E
B5: Revenue | C5: =Assumptions!C8 | D5: =Assumptions!D8 | E5: =Assumptions!E8 | F5: =Assumptions!F8 | G5: =Assumptions!G8 | H5: =Assumptions!H8
B6: EBITDA | C6: =Assumptions!C8*Assumptions!C10 | D6: =Assumptions!D8*Assumptions!D10 | E6: =Assumptions!E8*Assumptions!E10 | F6: =Assumptions!F8*Assumptions!F10 | G6: =Assumptions!G8*Assumptions!G10 | H6: =Assumptions!H8*Assumptions!H10
B7: (-) Depreciation & amortisation | C7: =-Assumptions!C8*Assumptions!C11 | D7: =-Assumptions!D8*Assumptions!D11 | E7: =-Assumptions!E8*Assumptions!E11 | F7: =-Assumptions!F8*Assumptions!F11 | G7: =-Assumptions!G8*Assumptions!G11 | H7: =-Assumptions!H8*Assumptions!H11
B8: EBIT | C8: =C6+C7 | D8: =D6+D7 | E8: =E6+E7 | F8: =F6+F7 | G8: =G6+G7 | H8: =H6+H7
B9: (-) Tax | C9: =-C8*Assumptions!C12 | D9: =-D8*Assumptions!D12 | E9: =-E8*Assumptions!E12 | F9: =-F8*Assumptions!F12 | G9: =-G8*Assumptions!G12 | H9: =-H8*Assumptions!H12
B10: NOPAT (EBIT after tax) | C10: =C8+C9 | D10: =D8+D9 | E10: =E8+E9 | F10: =F8+F9 | G10: =G8+G9 | H10: =H8+H9
B13: Margin checks (% of revenue)
C14: 2024A | D14: 2025E | E14: 2026E | F14: 2027E | G14: 2028E | H14: 2029E
B15: EBITDA margin | C15: =C6/C5 | D15: =D6/D5 | E15: =E6/E5 | F15: =F6/F5 | G15: =G6/G5 | H15: =H6/H5
B16: EBIT margin | C16: =C8/C5 | D16: =D8/D5 | E16: =E8/E5 | F16: =F8/F5 | G16: =G8/G5 | H16: =H8/H5

Sheet Free Cash Flow
B2: Free Cash Flow to Firm (DKK bn)
C4: 2024A | D4: 2025E | E4: 2026E | F4: 2027E | G4: 2028E | H4: 2029E
B5: NOPAT | C5: ='Income Statement'!C10 | D5: ='Income Statement'!D10 | E5: ='Income Statement'!E10 | F5: ='Income Statement'!F10 | G5: ='Income Statement'!G10 | H5: ='Income Statement'!H10
B6: (+) D&A (add back) | C6: =-'Income Statement'!C7 | D6: =-'Income Statement'!D7 | E6: =-'Income Statement'!E7 | F6: =-'Income Statement'!F7 | G6: =-'Income Statement'!G7 | H6: =-'Income Statement'!H7
B7: (-) Capex | C7: =-Assumptions!C8*Assumptions!C16 | D7: =-Assumptions!D8*Assumptions!D16 | E7: =-Assumptions!E8*Assumptions!E16 | F7: =-Assumptions!F8*Assumptions!F16 | G7: =-Assumptions!G8*Assumptions!G16 | H7: =-Assumptions!H8*Assumptions!H16
B8: (-) Change in working capital | C8: =-Assumptions!C8*Assumptions!C17 | D8: =-Assumptions!D8*Assumptions!D17 | E8: =-Assumptions!E8*Assumptions!E17 | F8: =-Assumptions!F8*Assumptions!F17 | G8: =-Assumptions!G8*Assumptions!G17 | H8: =-Assumptions!H8*Assumptions!H17
B9: Free Cash Flow | C9: =SUM(C5:C8) | D9: =SUM(D5:D8) | E9: =SUM(E5:E8) | F9: =SUM(F5:F8) | G9: =SUM(G5:G8) | H9: =SUM(H5:H8)
B11: Year (t) | C11: 0 | D11: 1 | E11: 2 | F11: 3 | G11: 4 | H11: 5
B12: Discount factor 1/(1+WACC)^t | C12: =1/((1+Assumptions!$C$21)^C11) | D12: =1/((1+Assumptions!$C$21)^D11) | E12: =1/((1+Assumptions!$C$21)^E11) | F12: =1/((1+Assumptions!$C$21)^F11) | G12: =1/((1+Assumptions!$C$21)^G11) | H12: =1/((1+Assumptions!$C$21)^H11)
B13: PV of FCF | C13: =C9*C12 | D13: =D9*D12 | E13: =E9*E12 | F13: =F9*F12 | G13: =G9*G12 | H13: =H9*H12
B15: Sum of PV(FCF) [excludes 2024A] | C15: =SUM(D13:H13)

Sheet WACC
B2: Weighted Average Cost of Capital
B4: Cost of equity (CAPM)
B5: Risk-free rate (DK 10Y govt yield) | C5: 0.025
B6: Equity risk premium | C6: 0.055
B7: Beta (5Y vs OMX) | C7: 1.05
B8: Cost of equity Ke = Rf + Beta * ERP | C8: =C5+C7*C6
B10: After-tax cost of debt
B11: Pre-tax cost of debt | C11: 0.04
B12: Tax rate | C12: =Assumptions!C12
B13: Cost of debt Kd = Pre-tax * (1 - tax) | C13: =C11*(1-C12)
B14: WACC
B15: WACC = E/V * Ke + D/V * Kd | C15: =0.6*C8+0.4*C13
B17: Note: Equity-to-debt weights set illustratively. In a real engagement, use market value of equity vs net debt at valuation date.

Sheet Valuation
B2: Enterprise and Equity Valuation (DKK bn)
B4: Enterprise value bridge
B5: Sum of PV(forecast FCFs) | C5: ='Free Cash Flow'!C15
B6: Terminal FCF (year 5 * (1+g)) | C6: ='Free Cash Flow'!H9*(1+Assumptions!C20)
B7: Terminal value at end-2029 | C7: =C6/(Assumptions!C21-Assumptions!C20)
B8: PV of terminal value | C8: =C7*'Free Cash Flow'!H12
B9: Enterprise Value | C9: =C5+C8
B10: (-) Net debt | C10: =-Assumptions!C24
B11: Equity Value (DKK bn) | C11: =C9+C10
B12: Diluted shares outstanding (millions) | C12: =Assumptions!C25
B13: Implied price per share (DKK) | C13: =C11*1000/C12
B15: Disclaimer: this is a teaching DCF using illustrative inputs. The implied price is not an investment recommendation.

Sheet Sensitivity
B2: Sensitivity: implied share price vs WACC and terminal growth
B4: Top axis: terminal growth rate (g). Left axis: WACC.
B6: WACC \ g | C6: 0.01 | D6: 0.015 | E6: 0.02 | F6: 0.025 | G6: 0.03
B7: 0.06 | C7: =((('Free Cash Flow'!D9/((1+B7)^1))+('Free Cash Flow'!E9/((1+B7)^2))+('Free Cash Flow'!F9/((1+B7)^3))+('Free Cash Flow'!G9/((1+B7)^4))+('Free Cash Flow'!H9/((1+B7)^5)))+(('Free Cash Flow'!H9*(1+0.01))/(B7-0.01))/((1+B7)^5)-Assumptions!$C$24)*1000/Assumptions!$C$25 | D7: =((('Free Cash Flow'!D9/((1+B7)^1))+('Free Cash Flow'!E9/((1+B7)^2))+('Free Cash Flow'!F9/((1+B7)^3))+('Free Cash Flow'!G9/((1+B7)^4))+('Free Cash Flow'!H9/((1+B7)^5)))+(('Free Cash Flow'!H9*(1+0.015))/(B7-0.015))/((1+B7)^5)-Assumptions!$C$24)*1000/Assumptions!$C$25 | E7: =((('Free Cash Flow'!D9/((1+B7)^1))+('Free Cash Flow'!E9/((1+B7)^2))+('Free Cash Flow'!F9/((1+B7)^3))+('Free Cash Flow'!G9/((1+B7)^4))+('Free Cash Flow'!H9/((1+B7)^5)))+(('Free Cash Flow'!H9*(1+0.02))/(B7-0.02))/((1+B7)^5)-Assumptions!$C$24)*1000/Assumptions!$C$25 | F7: =((('Free Cash Flow'!D9/((1+B7)^1))+('Free Cash Flow'!E9/((1+B7)^2))+('Free Cash Flow'!F9/((1+B7)^3))+('Free Cash Flow'!G9/((1+B7)^4))+('Free Cash Flow'!H9/((1+B7)^5)))+(('Free Cash Flow'!H9*(1+0.025))/(B7-0.025))/((1+B7)^5)-Assumptions!$C$24)*1000/Assumptions!$C$25 | G7: =((('Free Cash Flow'!D9/((1+B7)^1))+('Free Cash Flow'!E9/((1+B7)^2))+('Free Cash Flow'!F9/((1+B7)^3))+('Free Cash Flow'!G9/((1+B7)^4))+('Free Cash Flow'!H9/((1+B7)^5)))+(('Free Cash Flow'!H9*(1+0.03))/(B7-0.03))/((1+B7)^5)-Assumptions!$C$24)*1000/Assumptions!$C$25
B8: 0.065 | C8: =((('Free Cash Flow'!D9/((1+B8)^1))+('Free Cash Flow'!E9/((1+B8)^2))+('Free Cash Flow'!F9/((1+B8)^3))+('Free Cash Flow'!G9/((1+B8)^4))+('Free Cash Flow'!H9/((1+B8)^5)))+(('Free Cash Flow'!H9*(1+0.01))/(B8-0.01))/((1+B8)^5)-Assumptions!$C$24)*1000/Assumptions!$C$25 | D8: =((('Free Cash Flow'!D9/((1+B8)^1))+('Free Cash Flow'!E9/((1+B8)^2))+('Free Cash Flow'!F9/((1+B8)^3))+('Free Cash Flow'!G9/((1+B8)^4))+('Free Cash Flow'!H9/((1+B8)^5)))+(('Free Cash Flow'!H9*(1+0.015))/(B8-0.015))/((1+B8)^5)-Assumptions!$C$24)*1000/Assumptions!$C$25 | E8: =((('Free Cash Flow'!D9/((1+B8)^1))+('Free Cash Flow'!E9/((1+B8)^2))+('Free Cash Flow'!F9/((1+B8)^3))+('Free Cash Flow'!G9/((1+B8)^4))+('Free Cash Flow'!H9/((1+B8)^5)))+(('Free Cash Flow'!H9*(1+0.02))/(B8-0.02))/((1+B8)^5)-Assumptions!$C$24)*1000/Assumptions!$C$25 | F8: =((('Free Cash Flow'!D9/((1+B8)^1))+('Free Cash Flow'!E9/((1+B8)^2))+('Free Cash Flow'!F9/((1+B8)^3))+('Free Cash Flow'!G9/((1+B8)^4))+('Free Cash Flow'!H9/((1+B8)^5)))+(('Free Cash Flow'!H9*(1+0.025))/(B8-0.025))/((1+B8)^5)-Assumptions!$C$24)*1000/Assumptions!$C$25 | G8: =((('Free Cash Flow'!D9/((1+B8)^1))+('Free Cash Flow'!E9/((1+B8)^2))+('Free Cash Flow'!F9/((1+B8)^3))+('Free Cash Flow'!G9/((1+B8)^4))+('Free Cash Flow'!H9/((1+B8)^5)))+(('Free Cash Flow'!H9*(1+0.03))/(B8-0.03))/((1+B8)^5)-Assumptions!$C$24)*1000/Assumptions!$C$25
B9: 0.07 | C9: =((('Free Cash Flow'!D9/((1+B9)^1))+('Free Cash Flow'!E9/((1+B9)^2))+('Free Cash Flow'!F9/((1+B9)^3))+('Free Cash Flow'!G9/((1+B9)^4))+('Free Cash Flow'!H9/((1+B9)^5)))+(('Free Cash Flow'!H9*(1+0.01))/(B9-0.01))/((1+B9)^5)-Assumptions!$C$24)*1000/Assumptions!$C$25 | D9: =((('Free Cash Flow'!D9/((1+B9)^1))+('Free Cash Flow'!E9/((1+B9)^2))+('Free Cash Flow'!F9/((1+B9)^3))+('Free Cash Flow'!G9/((1+B9)^4))+('Free Cash Flow'!H9/((1+B9)^5)))+(('Free Cash Flow'!H9*(1+0.015))/(B9-0.015))/((1+B9)^5)-Assumptions!$C$24)*1000/Assumptions!$C$25 | E9: =((('Free Cash Flow'!D9/((1+B9)^1))+('Free Cash Flow'!E9/((1+B9)^2))+('Free Cash Flow'!F9/((1+B9)^3))+('Free Cash Flow'!G9/((1+B9)^4))+('Free Cash Flow'!H9/((1+B9)^5)))+(('Free Cash Flow'!H9*(1+0.02))/(B9-0.02))/((1+B9)^5)-Assumptions!$C$24)*1000/Assumptions!$C$25 | F9: =((('Free Cash Flow'!D9/((1+B9)^1))+('Free Cash Flow'!E9/((1+B9)^2))+('Free Cash Flow'!F9/((1+B9)^3))+('Free Cash Flow'!G9/((1+B9)^4))+('Free Cash Flow'!H9/((1+B9)^5)))+(('Free Cash Flow'!H9*(1+0.025))/(B9-0.025))/((1+B9)^5)-Assumptions!$C$24)*1000/Assumptions!$C$25 | G9: =((('Free Cash Flow'!D9/((1+B9)^1))+('Free Cash Flow'!E9/((1+B9)^2))+('Free Cash Flow'!F9/((1+B9)^3))+('Free Cash Flow'!G9/((1+B9)^4))+('Free Cash Flow'!H9/((1+B9)^5)))+(('Free Cash Flow'!H9*(1+0.03))/(B9-0.03))/((1+B9)^5)-Assumptions!$C$24)*1000/Assumptions!$C$25
B10: 0.075 | C10: =((('Free Cash Flow'!D9/((1+B10)^1))+('Free Cash Flow'!E9/((1+B10)^2))+('Free Cash Flow'!F9/((1+B10)^3))+('Free Cash Flow'!G9/((1+B10)^4))+('Free Cash Flow'!H9/((1+B10)^5)))+(('Free Cash Flow'!H9*(1+0.01))/(B10-0.01))/((1+B10)^5)-Assumptions!$C$24)*1000/Assumptions!$C$25 | D10: =((('Free Cash Flow'!D9/((1+B10)^1))+('Free Cash Flow'!E9/((1+B10)^2))+('Free Cash Flow'!F9/((1+B10)^3))+('Free Cash Flow'!G9/((1+B10)^4))+('Free Cash Flow'!H9/((1+B10)^5)))+(('Free Cash Flow'!H9*(1+0.015))/(B10-0.015))/((1+B10)^5)-Assumptions!$C$24)*1000/Assumptions!$C$25 | E10: =((('Free Cash Flow'!D9/((1+B10)^1))+('Free Cash Flow'!E9/((1+B10)^2))+('Free Cash Flow'!F9/((1+B10)^3))+('Free Cash Flow'!G9/((1+B10)^4))+('Free Cash Flow'!H9/((1+B10)^5)))+(('Free Cash Flow'!H9*(1+0.02))/(B10-0.02))/((1+B10)^5)-Assumptions!$C$24)*1000/Assumptions!$C$25 | F10: =((('Free Cash Flow'!D9/((1+B10)^1))+('Free Cash Flow'!E9/((1+B10)^2))+('Free Cash Flow'!F9/((1+B10)^3))+('Free Cash Flow'!G9/((1+B10)^4))+('Free Cash Flow'!H9/((1+B10)^5)))+(('Free Cash Flow'!H9*(1+0.025))/(B10-0.025))/((1+B10)^5)-Assumptions!$C$24)*1000/Assumptions!$C$25 | G10: =((('Free Cash Flow'!D9/((1+B10)^1))+('Free Cash Flow'!E9/((1+B10)^2))+('Free Cash Flow'!F9/((1+B10)^3))+('Free Cash Flow'!G9/((1+B10)^4))+('Free Cash Flow'!H9/((1+B10)^5)))+(('Free Cash Flow'!H9*(1+0.03))/(B10-0.03))/((1+B10)^5)-Assumptions!$C$24)*1000/Assumptions!$C$25
B11: 0.08 | C11: =((('Free Cash Flow'!D9/((1+B11)^1))+('Free Cash Flow'!E9/((1+B11)^2))+('Free Cash Flow'!F9/((1+B11)^3))+('Free Cash Flow'!G9/((1+B11)^4))+('Free Cash Flow'!H9/((1+B11)^5)))+(('Free Cash Flow'!H9*(1+0.01))/(B11-0.01))/((1+B11)^5)-Assumptions!$C$24)*1000/Assumptions!$C$25 | D11: =((('Free Cash Flow'!D9/((1+B11)^1))+('Free Cash Flow'!E9/((1+B11)^2))+('Free Cash Flow'!F9/((1+B11)^3))+('Free Cash Flow'!G9/((1+B11)^4))+('Free Cash Flow'!H9/((1+B11)^5)))+(('Free Cash Flow'!H9*(1+0.015))/(B11-0.015))/((1+B11)^5)-Assumptions!$C$24)*1000/Assumptions!$C$25 | E11: =((('Free Cash Flow'!D9/((1+B11)^1))+('Free Cash Flow'!E9/((1+B11)^2))+('Free Cash Flow'!F9/((1+B11)^3))+('Free Cash Flow'!G9/((1+B11)^4))+('Free Cash Flow'!H9/((1+B11)^5)))+(('Free Cash Flow'!H9*(1+0.02))/(B11-0.02))/((1+B11)^5)-Assumptions!$C$24)*1000/Assumptions!$C$25 | F11: =((('Free Cash Flow'!D9/((1+B11)^1))+('Free Cash Flow'!E9/((1+B11)^2))+('Free Cash Flow'!F9/((1+B11)^3))+('Free Cash Flow'!G9/((1+B11)^4))+('Free Cash Flow'!H9/((1+B11)^5)))+(('Free Cash Flow'!H9*(1+0.025))/(B11-0.025))/((1+B11)^5)-Assumptions!$C$24)*1000/Assumptions!$C$25 | G11: =((('Free Cash Flow'!D9/((1+B11)^1))+('Free Cash Flow'!E9/((1+B11)^2))+('Free Cash Flow'!F9/((1+B11)^3))+('Free Cash Flow'!G9/((1+B11)^4))+('Free Cash Flow'!H9/((1+B11)^5)))+(('Free Cash Flow'!H9*(1+0.03))/(B11-0.03))/((1+B11)^5)-Assumptions!$C$24)*1000/Assumptions!$C$25
B14: Read: each cell = implied DKK share price under that combination of WACC and terminal growth.
